{"LQI2AbamnbVJ7Sej9BWqjA==":"mbr-122x232.jpg","u/Mpm7TnTwVuxe9k1LpIIQ==":"mbr-376x251.jpg","Z58qC2Nki7l+qqcxoXchsQ==":"brand.ico","9at0bomXrQhn+VJbmdDUFw==":"mbr-1920x1440.jpg","UcAwTKpjg/xHyQftx3XNUA==":"bg-2000x1333.jpg","L3p6PZL4lHf/Sb5uTv6qgg==":"mbr-676x1352.jpg","0Dd+n/fL6/cw7+amZ+WKLQ==":"mbr-676x451.jpg","wfDe6Wj5QJzyNQ3GxfN2rg==":"orange-1-842x380.png","SxBVH+V9oOWYi6AVQvTN9g==":"data-tracer-masker-in-chakra-max-partner-1-165x100.jpg","8Q+bIZnjMjVLjvyYNBrleQ==":"nvr-partner-cnb.png.gif","iWa+8onTsID1a5UX1tIrkQ==":"nvr-partner-kny-ccty-478x100.png","uQAjLE3pOjL1G/80+W5fdQ==":"nvr-partner-cnb-499x100.png","NS9KYZFnD2NtUypvbh8wcg==":"nvr-partner-cnb-120x100.png","U09h8XfRQHtFuOJAqoz60g==":"nvr-partner-kny-ccty-500x100.png","/yQRSJPXYFM0Wl1+OlB3iQ==":"nvr-partner-cnb-500x100.png","Q2vfNHoJxsSvHdfxojrR4g==":"nvr-partner-cnb-436x100.png","HEgbwPj9OqqWXxdgB7pSWg==":"nvr-partner-cnb-1-436x100.png","7JBegxO2Mxez/87f4sH4Rw==":"cnb-partner-436x100.jpg","UndM/pESxXB9+hXdKRnObw==":"kny-cctv-partner-500x100.jpg","P+rSWzTGRkvgtiz6VaI5xA==":"kny-cctv-partner-421x100.jpg","/pmvo+zumi0zDU1/Xu+Obw==":"cnb-partner-313x100.jpg","jl/5zY31GCrUHJwuXsH9hg==":"cnb-partner-1-313x100.jpg","7lZ1gAtH/cPFrMHkpw+KPQ==":"cnb-partner-2-313x100.jpg","5SfjY6AClc3E/D3FkfZQ1g==":"cnb-partner-3-313x100.jpg","khSj1YsapAj652Xn8J0ofQ==":"mbr-1920x1280.jpg","PKvsgc1hwYq5txr5l7ISOQ==":"mbr-1-1920x1280.jpg","zmZ0734pa8bjhYY0dlKbcw==":"mbr-1920x1080.jpg","e9sxPgGRO9Ti2koPNE0G0Q==":"mbr-2-1920x1280.jpg","kRBbRgR3CARSCmF/d7sWWQ==":"mbr-1920x1275.jpg","IMN841Xi+PcdFAcgLUkKUw==":"mbr-1-1920x1275.jpg","0EPEJ2bG0+65uCzo8KrlBg==":"mbr-3-1920x1280.jpg","embXRF5FHb8qikbJSz/9SA==":"mbr-1-1920x1440.jpg","k1EjM57F9wSAD6mU11yOGA==":"mbr-4-1920x1280.jpg","T4yfA4WbdkyNfLz987zRmw==":"mbr-1920x1289.jpg","iv869NV6KbBkZr8QITclLw==":"mbr-1920x1386.jpg","gp0k8ZiyRNFDwldwXdnLyg==":"mbr-2-1920x1275.jpg","QNzrtZQTPm3CX/q6iyjFEA==":"mbr-3-1920x1275.jpg","jNhlAt8Zs6fXpg40rSEqYA==":"mbr-4-1920x1275.jpg","iF2x1vgHNv5Z6lLaNJ7vHw==":"mbr-5-1920x1275.jpg","VvBMoDR43yKvJlq/tTivLA==":"mbr-6-1920x1275.jpg","NqqV6nhOtQ8qkK4pBTjosg==":"mbr-5-1920x1280.jpg","M7/3EKuJTxyQFCKBsJMVeQ==":"mbr-7-1920x1275.jpg","b1cYlq436OcKLhXxyw577w==":"mbr-6-1920x1280.jpg","132BRK15B9L3RTQzn1Dxhg==":"mbr-7-1920x1280.jpg","JfVSRPw0/nM1hg7OtLOBSw==":"mbr-8-1920x1280.jpg","qGAAhqiTS84kLQl23yZrNQ==":"mbr-1920x700.jpg","4gTOIJ4ZZiMLnFLXkXFmbQ==":"mbr-1-1920x700.jpg","J5yuJpUjGjd/YLJQdGRJcw==":"mbr-2-1920x700.jpg","ScJMuIAUWqS9qmVbNoRl8g==":"mbr-3-1920x700.jpg","EOAncxMH3Uvm4KCWk+FA0Q==":"mbr-4-1920x700.jpg","dM9m5HNOjvKqiGd1D3QiPg==":"mbr-5-1920x700.jpg","lDtfCS/cEwXLC+dc9aZm/Q==":"mbr-1920x1281.jpg","CZemN9yrfGmgYqBGPXuVnQ==":"mbr-1920x1005.jpg","4gpIUiOE85O41RcW7s4vMg==":"mbr-1-1920x1005.jpg","J9Z/a2kzRhDaiEPF5fVRLw==":"mbr-2-1920x1005.jpg","IfVXwrX2PLNJ2tA9Vb4/Ow==":"mbr-3-1920x1005.jpg","JuT5MeOWGrPsjAgSv18vKg==":"mbr-1920x639.jpg","gJqACnRzzenqUUVqBVZrhg==":"mbr-192x120.jpg","aito36ibQ0ED05LeU2Xtzg==":"mbr-308x116.jpg"}